FullStackPythonZhongwenbanFix1/README.md
FullStackPythonZhongwenbanFix1/__init__.py
FullStackPythonZhongwenbanFix1/__main__.py
FullStackPythonZhongwenbanFix1/file.epub
FullStackPythonZhongwenbanFix1/index.html
FullStackPythonZhongwenbanFix1/css/__init__.py
FullStackPythonZhongwenbanFix1/css/annotations.css
FullStackPythonZhongwenbanFix1/css/main.css
FullStackPythonZhongwenbanFix1/css/normalize.css
FullStackPythonZhongwenbanFix1/css/popup.css
FullStackPythonZhongwenbanFix1/font/__init__.py
FullStackPythonZhongwenbanFix1/font/fontello.eot
FullStackPythonZhongwenbanFix1/font/fontello.svg
FullStackPythonZhongwenbanFix1/font/fontello.ttf
FullStackPythonZhongwenbanFix1/font/fontello.woff
FullStackPythonZhongwenbanFix1/img/__init__.py
FullStackPythonZhongwenbanFix1/img/annotator-glyph-sprite.png
FullStackPythonZhongwenbanFix1/img/annotator-icon-sprite.png
FullStackPythonZhongwenbanFix1/img/apple-touch-icon.png
FullStackPythonZhongwenbanFix1/img/cancelfullscreen.png
FullStackPythonZhongwenbanFix1/img/close.png
FullStackPythonZhongwenbanFix1/img/fullscreen.png
FullStackPythonZhongwenbanFix1/img/loader.gif
FullStackPythonZhongwenbanFix1/img/menu-icon.png
FullStackPythonZhongwenbanFix1/img/save.png
FullStackPythonZhongwenbanFix1/img/saved.png
FullStackPythonZhongwenbanFix1/img/settings-s.png
FullStackPythonZhongwenbanFix1/img/settings.png
FullStackPythonZhongwenbanFix1/img/star.png
FullStackPythonZhongwenbanFix1/js/__init__.py
FullStackPythonZhongwenbanFix1/js/epub.js
FullStackPythonZhongwenbanFix1/js/epub.min.js
FullStackPythonZhongwenbanFix1/js/epub.min.map
FullStackPythonZhongwenbanFix1/js/hooks.min.js
FullStackPythonZhongwenbanFix1/js/hooks.min.map
FullStackPythonZhongwenbanFix1/js/reader.js
FullStackPythonZhongwenbanFix1/js/reader.js.map
FullStackPythonZhongwenbanFix1/js/reader.min.js
FullStackPythonZhongwenbanFix1/js/reader.min.map
FullStackPythonZhongwenbanFix1/js/hooks/__init__.py
FullStackPythonZhongwenbanFix1/js/hooks/extensions/__init__.py
full_stack_python_zhongwenban_fix1-2025.3.24.1.dist-info/METADATA
full_stack_python_zhongwenban_fix1-2025.3.24.1.dist-info/WHEEL
full_stack_python_zhongwenban_fix1-2025.3.24.1.dist-info/entry_points.txt
full_stack_python_zhongwenban_fix1-2025.3.24.1.dist-info/top_level.txt
full_stack_python_zhongwenban_fix1-2025.3.24.1.dist-info/RECORD
